lmwsip/__init__.py
lmwsip/run.py
lmwsip-0.9.10.dist-info/licenses/LICENSE
lmwsip-0.9.10.dist-info/METADATA
lmwsip-0.9.10.dist-info/WHEEL
lmwsip-0.9.10.dist-info/top_level.txt
lmwsip-0.9.10.dist-info/RECORD
