Metadata-Version: 2.4
Name: lmwsip
Version: 0.9.10
Summary: Interface for the lmw sip protocol
Home-page: https://git.marceln.org/Werk/lmwsip
Author: Marcel Nijenhof
Author-email: pypi@marceln.org
Classifier: Programming Language :: Python :: 3
Classifier: License :: OSI Approved :: MIT License
Classifier: Operating System :: OS Independent
Classifier: Development Status :: 4 - Beta
Requires-Python: >=3.6
License-File: LICENSE
Requires-Dist: python-dateutil
Dynamic: license-file
